mev_commit_sdk_py/helpers.py
mev_commit_sdk_py/hypersync_client.py
mev_commit_sdk_py-0.4.8.dist-info/METADATA
mev_commit_sdk_py-0.4.8.dist-info/WHEEL
mev_commit_sdk_py-0.4.8.dist-info/RECORD
