Metadata-Version: 2.3
Name: mev-commit-sdk-py
Version: 0.4.8
Summary: mev-commit python sdk for on-chain data retrieval for mev-commit chain
Author-email: Evan K <evan@primev.xyz>
Requires-Python: >=3.12
Requires-Dist: bump2version>=1.0.1
Requires-Dist: git-changelog>=2.5.2
Requires-Dist: hypersync>=0.8.3
Requires-Dist: polars>=1.0.0
Requires-Dist: pyarrow>=16.0.0
Requires-Dist: python-dotenv>=1.0.1
